{
  "damage": {
    "broken": {
      "name": "Broken",
      "drop-rate": 50,
      "empower-stats": [{
        "category": "bow",
        "stats": {
          "damage-multiplier": -0.15
        }
      }]
    },
    "rusty": {
      "name": "Rusty",
      "drop-rate": 75,
      "empower-stats": [{
        "category": "bow",
        "stats": {
          "damage-multiplier": -0.1
        }
      }]
    },
    "blunt": {
      "name": "Blunt",
      "empower-stats": [{
        "category": "bow",
        "stats": {
          "damage-multiplier": -0.05
        }
      }]
    },
    "sharp": {
      "name": "Sharp",
      "empower-stats": [{
        "category": "bow",
        "stats": {
          "damage-multiplier": 0.05
        }
      }]
    },
    "ruthless": {
      "name": "Ruthless",
      "drop-rate": 75,
      "empower-stats": [{
        "category": "bow",
        "stats": {
          "damage-multiplier": 0.1
        }
      }]
    },
    "deadly": {
      "name": "Deadly",
      "drop-rate": 50,
      "empower-stats": [{
        "category": "bow",
        "stats": {
          "damage-multiplier": 0.15
        }
      }]
    }
  },

  "attack-speed": {
    "slow": {
      "name": "Slow",
      "drop-rate": 50,
      "empower-stats": [{
        "category": "bow",
        "stats": {
          "attack-speed": -0.15
        }
      }]
    },
    "lazy": {
      "name": "Lazy",
      "drop-rate": 75,
      "empower-stats": [{
        "category": "bow",
        "stats": {
          "attack-speed": -0.1
        }
      }]
    },
    "heavy": {
      "name": "Heavy",
      "empower-stats": [{
        "category": "bow",
        "stats": {
          "attack-speed": -0.1
        }
      }]
    },
    "nimble": {
      "name": "Nimble",
      "empower-stats": [{
        "category": "bow",
        "stats": {
          "attack-speed": 0.05
        }
      }]
    },
    "quick": {
      "name": "Quick",
      "drop-rate": 75,
      "empower-stats": [{
        "category": "bow",
        "stats": {
          "attack-speed": 0.1
        }
      }]
    },
    "rapid": {
      "name": "Rapid",
      "drop-rate": 50,
      "empower-stats": [{
        "category": "bow",
        "stats": {
          "attack-speed": 0.15
        }
      }]
    }
  },

  "crit-chance": {
    "inaccurate": {
      "name": "Inaccurate",
      "drop-rate": 50,
      "empower-stats": [{
        "category": "bow",
        "stats": {
          "crit-chance": -0.15
        }
      }]
    },
    "inexact": {
      "name": "Inexact",
      "drop-rate": 75,
      "empower-stats": [{
        "category": "bow",
        "stats": {
          "crit-chance": -0.1
        }
      }]
    },
    "uncertain": {
      "name": "Uncertain",
      "empower-stats": [{
        "category": "bow",
        "stats": {
          "crit-chance": -0.05
        }
      }]
    },
    "aiming": {
      "name": "Aiming",
      "empower-stats": [{
        "category": "bow",
        "stats": {
          "crit-chance": 0.05
        }
      }]
    },
    "piercing": {
      "name": "Piercing",
      "drop-rate": 75,
      "empower-stats": [{
        "category": "bow",
        "stats": {
          "crit-chance": 0.1
        }
      }]
    },
    "precise": {
      "name": "Precise",
      "drop-rate": 50,
      "empower-stats": [{
        "category": "bow",
        "stats": {
          "crit-chance": 0.15
        }
      }]
    }
  },

  "crit-damage": {
    "harmless": {
      "name": "Harmless",
      "drop-rate": 50,
      "empower-stats": [{
        "category": "bow",
        "stats": {
          "crit-damage": -0.3
        }
      }]
    },
    "kind": {
      "name": "Kind",
      "drop-rate": 75,
      "empower-stats": [{
        "category": "bow",
        "stats": {
          "crit-damage": -0.2
        }
      }]
    },
    "safe": {
      "name": "Safe",
      "empower-stats": [{
        "category": "bow",
        "stats": {
          "crit-damage": -0.1
        }
      }]
    },
    "crushing": {
      "name": "Crushing",
      "empower-stats": [{
        "category": "bow",
        "stats": {
          "crit-damage": 0.1
        }
      }]
    },
    "demolishing": {
      "name": "Demolishing",
      "drop-rate": 75,
      "empower-stats": [{
        "category": "bow",
        "stats": {
          "crit-damage": 0.2
        }
      }]
    },
    "obliterating": {
      "name": "Obliterating",
      "drop-rate": 50,
      "empower-stats": [{
        "category": "bow",
        "stats": {
          "crit-damage": 0.3
        }
      }]
    }
  },

  "bleed-chance": {
    "cutting": {
      "name": "Cutting",
      "empower-stats": [{
        "category": "bow",
        "stats": {
          "bleed-chance": 0.1,
          "bleed-duration": 1
        }
      }]
    },
    "slicing": {
      "name": "Slicing",
      "drop-rate": 75,
      "empower-stats": [{
        "category": "bow",
        "stats": {
          "bleed-chance": 0.2,
          "bleed-duration": 1
        }
      }]
    },
    "slashing": {
      "name": "Slashing",
      "drop-rate": 50,
      "empower-stats": [{
        "category": "bow",
        "stats": {
          "bleed-chance": 0.3,
          "bleed-duration": 1
        }
      }]
    }
  },

  "bleed-duration": {
    "ripping": {
      "name": "Ripping",
      "empower-stats": [{
        "category": "bow",
        "stats": {
          "bleed-duration": 1
        }
      }]
    },
    "tearing": {
      "name": "Tearing",
      "drop-rate": 75,
      "empower-stats": [{
        "category": "bow",
        "stats": {
          "bleed-duration": 2
        }
      }]
    },
    "rupturing": {
      "name": "Rupturing",
      "drop-rate": 50,
      "empower-stats": [{
        "category": "bow",
        "stats": {
          "bleed-duration": 3
        }
      }]
    }
  }
}
