{
  "torso": {
    "leather-shirt": {
      "name": "Leather Shirt",
      "slot": "torso",
      "attack": false,
      "icon": "itemchestpiece",
      "drop-rate": 125,
      "character-stats": {
        "max-health": 20
      }
    },
    "iron-chestpiece": {
      "name": "Iron Chestpiece",
      "slot": "torso",
      "attack": false,
      "icon": "itemchestpiece",
      "character-stats": {
        "max-health": 30,
        "block-chance": -0.15
      }
    },
    "lamellar-chestpiece": {
      "name": "Lamellar Chestpiece",
      "slot": "torso",
      "attack": false,
      "icon": "itemchestpiece",
      "character-stats": {
        "block-chance": 0.1
      }
    },
    "bedrock-chestplate": {
      "name": "Bedrock Chestplate",
      "slot": "torso",
      "attack": false,
      "icon": "itemchestpiece",
      "drop-rate": 75,
      "character-stats": {
        "max-health": 60,
        "hit-chance": -0.4
      },
      "description": "Legends tell tales of a chestpiece so powerful that no mortal man could damage it. This is not that chestpiece."
    },
    "linen-tunic": {
      "name": "Linen Tunic",
      "slot": "torso",
      "attack": false,
      "icon": "itemchestpiece",
      "character-stats": {
        "max-health": -15,
        "hit-chance": 0.2
      }
    }
  }
}
